surfer_protocol/__init__.py
surfer_protocol/client.py
surfer_protocol-0.1.2.dist-info/LICENSE
surfer_protocol-0.1.2.dist-info/METADATA
surfer_protocol-0.1.2.dist-info/WHEEL
surfer_protocol-0.1.2.dist-info/top_level.txt
surfer_protocol-0.1.2.dist-info/RECORD
